[
  {
    "title": "MIRAVI - Жду тебя (Official Music Video, 2025)",
    "videoId": "bS0OEZssnTo",
    "published": "2025-03-24T23:50:22Z"
  },
  {
    "title": "MIRAVI - Жду тебя (Music)",
    "videoId": "OEWZEP7CiF8",
    "published": "2025-03-24T23:50:34Z"
  },
  {
    "title": "MIRAVI, Полина Гагарина - Опять метель (Live)",
    "videoId": "RKMBtGLGKGk",
    "published": "2025-03-24T23:50:46Z"
  },
  {
    "title": "Vlada MIRAVI - Рябина (Live in Moscow, 2024)",
    "videoId": "9aRZBOX2T7w",
    "published": "2025-03-24T23:50:57Z"
  },
  {
    "title": "Vlada MIRAVI - Воля (Live in Moscow, 2024)",
    "videoId": "EuuKjkNHD9k",
    "published": "2025-03-24T23:51:06Z"
  },
  {
    "title": "Vlada MIRAVI - More (Live in Moscow, 2024)",
    "videoId": "Jy-bMj7gj6s",
    "published": "2025-03-24T23:51:13Z"
  },
  {
    "title": "Vlada MIRAVI - За речкой (Live in Moscow, 2024)",
    "videoId": "1fs1ojtHTwI",
    "published": "2025-03-24T23:51:20Z"
  },
  {
    "title": "Vlada MIRAVI - Полюшко (Live in Moscow, 2024)",
    "videoId": "kvLgLSDBuV4",
    "published": "2025-03-24T23:51:26Z"
  },
  {
    "title": "Vlada MIRAVI - Вселенная (Live in Moscow, 2024)",
    "videoId": "6ZRruyL2em0",
    "published": "2025-03-24T23:51:31Z"
  },
  {
    "title": "МУЗ.ЛИТ: MIRAVI - Воля [Live]",
    "videoId": "_yF-gGXLJm4",
    "published": "2025-03-26T19:41:13Z"
  }
] 